MANIFEST.in
README.md
setup.cfg
setup.py
django_celery_errorlog.egg-info/PKG-INFO
django_celery_errorlog.egg-info/SOURCES.txt
django_celery_errorlog.egg-info/dependency_links.txt
django_celery_errorlog.egg-info/pbr.json
django_celery_errorlog.egg-info/requires.txt
django_celery_errorlog.egg-info/top_level.txt
djcelery_errorlog/__init__.py
djcelery_errorlog/models.py
djcelery_errorlog/migrations/0001_initial.py
djcelery_errorlog/migrations/__init__.py